dagster_faculty/__init__.py
dagster_faculty/example.py
dagster_faculty-0.1.3.dist-info/LICENSE
dagster_faculty-0.1.3.dist-info/METADATA
dagster_faculty-0.1.3.dist-info/WHEEL
dagster_faculty-0.1.3.dist-info/top_level.txt
dagster_faculty-0.1.3.dist-info/RECORD
